mfd_sysctl/__init__.py
mfd_sysctl/enums.py
mfd_sysctl/exceptions.py
mfd_sysctl/freebsd.py
mfd_sysctl/linux.py
mfd_sysctl/mfd_sysctl.py
mfd_sysctl-1.6.0.dist-info/licenses/AUTHORS.md
mfd_sysctl-1.6.0.dist-info/licenses/LICENSE.md
mfd_sysctl-1.6.0.dist-info/METADATA
mfd_sysctl-1.6.0.dist-info/WHEEL
mfd_sysctl-1.6.0.dist-info/top_level.txt
mfd_sysctl-1.6.0.dist-info/RECORD
